{
  "descriptionHash": "02E7801AC2F680560B3835101E33F40D0BE493C1FD7041CD1DF61DC2A7DFE005CCCEEC43A05EC6BAF2AC0ABC70ECD97ED7528FC95A137F6AC279C23571270435",
  "descriptionLocation": "https://api.hubspot.com/public/api/spec/v2/specs/release/75355/version/2026-03",
  "lockFileVersion": "1.0.0",
  "kiotaVersion": "1.29.0",
  "clientClassName": "HubSpotCRMPublicAppCrmCardsV202603Client",
  "typeAccessModifier": "Public",
  "clientNamespaceName": "DamianH.HubSpot.KiotaClient.CRM.PublicAppCrmCards.V202603",
  "language": "CSharp",
  "usesBackingStore": false,
  "excludeBackwardCompatible": false,
  "includeAdditionalData": true,
  "disableSSLValidation": false,
  "serializers": [
    "Microsoft.Kiota.Serialization.Json.JsonSerializationWriterFactory",
    "Microsoft.Kiota.Serialization.Text.TextSerializationWriterFactory",
    "Microsoft.Kiota.Serialization.Form.FormSerializationWriterFactory",
    "Microsoft.Kiota.Serialization.Multipart.MultipartSerializationWriterFactory"
  ],
  "deserializers": [
    "Microsoft.Kiota.Serialization.Json.JsonParseNodeFactory",
    "Microsoft.Kiota.Serialization.Text.TextParseNodeFactory",
    "Microsoft.Kiota.Serialization.Form.FormParseNodeFactory"
  ],
  "structuredMimeTypes": [
    "application/json",
    "text/plain;q=0.9",
    "application/x-www-form-urlencoded;q=0.2",
    "multipart/form-data;q=0.1"
  ],
  "includePatterns": [],
  "excludePatterns": [],
  "disabledValidationRules": []
}