{
  "descriptionHash": "E0856ABA3484CF01549B589F60038E7CF102273D892CC6E5322B0B39F78B1172AF1738A1244C4BA38A30D85FFB6E1A42D7E6833FE67B6AA34CA307EBF6376282",
  "descriptionLocation": "https://api.hubspot.com/public/api/spec/v1/specs/CRM/App%20Uninstalls/versions/209039",
  "lockFileVersion": "1.0.0",
  "kiotaVersion": "1.29.0",
  "clientClassName": "HubSpotCRMAppUninstallsV3Client",
  "typeAccessModifier": "Public",
  "clientNamespaceName": "DamianH.HubSpot.KiotaClient.CRM.AppUninstalls.V3",
  "language": "CSharp",
  "usesBackingStore": false,
  "excludeBackwardCompatible": false,
  "includeAdditionalData": true,
  "disableSSLValidation": false,
  "serializers": [
    "Microsoft.Kiota.Serialization.Json.JsonSerializationWriterFactory",
    "Microsoft.Kiota.Serialization.Text.TextSerializationWriterFactory",
    "Microsoft.Kiota.Serialization.Form.FormSerializationWriterFactory",
    "Microsoft.Kiota.Serialization.Multipart.MultipartSerializationWriterFactory"
  ],
  "deserializers": [
    "Microsoft.Kiota.Serialization.Json.JsonParseNodeFactory",
    "Microsoft.Kiota.Serialization.Text.TextParseNodeFactory",
    "Microsoft.Kiota.Serialization.Form.FormParseNodeFactory"
  ],
  "structuredMimeTypes": [
    "application/json",
    "text/plain;q=0.9",
    "application/x-www-form-urlencoded;q=0.2",
    "multipart/form-data;q=0.1"
  ],
  "includePatterns": [],
  "excludePatterns": [],
  "disabledValidationRules": []
}